rtl/day04/pc.v
module pc (
    input clk,          // Clock signal
    input rst,          // Asynchronous reset (reboots PC to 0)
    output reg [31:0] pc_out // 32-bit output holding the current address
);

    // Triggers on the rising edge of the clock or reset
    always @(posedge clk or posedge rst) begin
        if (rst) begin
            pc_out <= 32'h00000000; // Reset PC to address 0
        end else begin
            pc_out <= pc_out + 4;   // Increment by 4 bytes every cycle
        end
    end

endmodule

rtl/day04/tb_pc.v
module tb_pc;
    reg clk;
    reg rst;
    wire [31:0] pc_out;

    // Connect our testing rig to the Program Counter
    pc uut (
        .clk(clk),
        .rst(rst),
        .pc_out(pc_out)
    );

    // 1. Generate a continuous clock (toggles every 5 time units)
    initial begin
        clk = 0;
        forever #5 clk = ~clk;
    end

    // 2. Run the test sequence
    initial begin
        // Setup waveform file for GTKwave
        $dumpfile("pc_wave.vcd");
        $dumpvars(0, tb_pc);

        // Monitor the PC value in Hexadecimal formatting (%h)
        $monitor("Time=%0td | rst=%b | PC=0x%h (%0d)", $time, rst, pc_out, pc_out);

        // Start with a Reset
        rst = 1; #12; 
        rst = 0; // Release reset to let the PC start counting
        
        // Let it run for several clock cycles
        #80;

        $finish; // End simulation
    end
endmodule

rtl/day04/pc_wave.vcd
$date
	Fri Sep  4 10:41:19 2026
$end
$version
	Icarus Verilog
$end
$timescale
	1s
$end
$scope module tb_pc $end
$var wire 32 ! pc_out [31:0] $end
$var reg 1 " clk $end
$var reg 1 # rst $end
$scope module uut $end
$var wire 1 " clk $end
$var wire 1 # rst $end
$var reg 32 $ pc_out [31:0] $end
$upscope $end
$upscope $end
$enddefinitions $end
$comment Show the parameter values. $end
$dumpall
$end
#0
$dumpvars
b0 $
1#
0"
b0 !
$end
#5
1"
#10
0"
#12
0#
#15
b100 !
b100 $
1"
#20
0"
#25
b1000 !
b1000 $
1"
#30
0"
#35
b1100 !
b1100 $
1"
#40
0"
#45
b10000 !
b10000 $
1"
#50
0"
#55
b10100 !
b10100 $
1"
#60
0"
#65
b11000 !
b11000 $
1"
#70
0"
#75
b11100 !
b11100 $
1"
#80
0"
#85
b100000 !
b100000 $
1"
